smana/__init__.py
smana/auxiliary_routines.py
smana/smana.py
smana/utility.py
smana-0.1.2.dist-info/LICENSE.txt
smana-0.1.2.dist-info/METADATA
smana-0.1.2.dist-info/WHEEL
smana-0.1.2.dist-info/top_level.txt
smana-0.1.2.dist-info/RECORD
