Metadata-Version: 2.1
Name: smana
Version: 0.1.2
Summary: Repairing tool for time series with weekly seasonality
Author-email: "ToBe Analytics s.r.l." <info@tobe-analytics.com>
License: BSD 3-Clause License
Project-URL: homepage, https://tobe-analytics.com
Project-URL: repository, https://github.com/ToBe-Analytics/smana
Classifier: Development Status :: 4 - Beta
Classifier: Environment :: Console
Classifier: Intended Audience :: Science/Research
Classifier: License :: OSI Approved :: BSD License
Classifier: Operating System :: OS Independent
Classifier: Programming Language :: Python
Classifier: Programming Language :: Python :: 3
Classifier: Programming Language :: Python :: 3 :: Only
Classifier: Programming Language :: Python :: 3.7
Classifier: Programming Language :: Python :: 3.8
Classifier: Programming Language :: Python :: 3.9
Classifier: Programming Language :: Python :: 3.10
Classifier: Programming Language :: Python :: 3.11
Classifier: Programming Language :: Python :: 3.12
Classifier: Topic :: Scientific/Engineering
Requires-Python: >=3.7
License-File: LICENSE.txt
Requires-Dist: statsmodels <0.15,>=0.12
Requires-Dist: pandas <2.3,>=1.4
Requires-Dist: numpy <1.27,>=1.22
